ipyvuetify_app/__init__.py
ipyvuetify_app/app.py
ipyvuetify_app/router_example.py
ipyvuetify_app-0.1.6.dist-info/LICENSE.txt
ipyvuetify_app-0.1.6.dist-info/WHEEL
ipyvuetify_app-0.1.6.dist-info/METADATA
ipyvuetify_app-0.1.6.dist-info/RECORD
